modernqueue.py
modernqueue-1.0.3.dist-info/METADATA
modernqueue-1.0.3.dist-info/WHEEL
modernqueue-1.0.3.dist-info/top_level.txt
modernqueue-1.0.3.dist-info/RECORD
