Metadata-Version: 2.1
Name: modernqueue
Version: 1.0.3
Summary: A modern queue in a multithreaded environment
Author: Margot Louis
Keywords: thread,queue,modern
Classifier: Programming Language :: Python :: 3
Classifier: Operating System :: OS Independent
Requires-Python: >=3.6
